Workbook

Sheet June
A1: NAMA PERUSAHAAN | AG1: PT DEMO NUSANTARA
A2: GAJI BULAN | AG2: June 2026
A3: PERIODE | AG3: 22Mayr s/d 21 June 2026
A4: PEMBAYARAN | AG4: -
A5: 1 | B5: =A5+1 -> 2 | C5: =B5+1 -> 3 | D5: =C5+1 -> 4 | E5: =D5+1 -> 5 | F5: =E5+1 -> 6 | G5: =F5+1 -> 7 | H5: =G5+1 -> 8 | I5: =H5+1 -> 9 | ... BG5: =BF5+1 -> 59
A6: NO | B6: N A M A | G6: NIK | H6: STATUS | I6: Sisa Cuti | J6: TB <30 | K6: TB >30 | L6: C | M6: S | N6: I | O6: A | P6: TARIF | X6: PENDAPATAN | AO6: Jml Pendapatan | AP6: POTONGAN 1 | AR6: Jml Pendapatan | AS6: POTONGAN 2 | AX6: Jml Pendapatan | BC6: Dasar Perhitungan BPJS - TK | BD6: Dasar Perhitungan BPJS - KES | BF6: Tunjangan Pph21
C7: NO REK. | D7: JABATAN | E7: LOKASI | F7: TGL. MASUK | P7: HK | Q7: UH | R7: 1 | S7: LEMBUR | T7: Instf. Kerajinan | V7: HK | W7: Pot. Absensi | X7: GAJI POKOK | Y7: UH | Z7: Instf. Kerajinan | AA7: Tunj. Antar Cabang | AB7: Tunj. Komunikasi | AC7: tunj. Kost / U. Obat | AD7: Tunj. Jabatan | AE7: Instf. Prestasi | AF7: LEMBUR | AG7: Gaji | AH7: JHT-P & Pens | AI7: JKK & JKM | AJ7: BPJS-P | AK7: Tunj. BPJS | AL7: THR | AM7: Pesangon (info) | AN7: Tunj. PPh21 | AO7: GROSS 1 | AP7: Pot. Absensi | AQ7: Pot. BPJS TK Beban Kary | AR7: GROSS 2 | AS7: PINJAMAN | AT7: Pot. Tunj BPJS | AU7: BPJS-K | AV7: PPh21 | AW7: Ttl. Potongan | AX7: NETT | AZ7: Kes | BA7: TK
AH8: 0.057 | AI8: 0.0054 | AJ8: 0.04 | AQ8: 0.03 | AT8: 0.1024 | AU8: 0.01
S9: =600000/2 -> 300000 | Y9: =+P9*Q9 -> 0 | Z9: =+U9*T9 -> 0 | AF9: =S9*R9 -> 0 | AG9: =SUM(X9:AF9) -> 0 | AH9: =$AH$8*BC9 -> 0 | AI9: =$AI$8*BC9 -> 0 | AJ9: =$AJ$8*BD9 -> 0 | AK9: =SUM(AH9:AJ9) -> 0 | AN9: =BF9 -> 0 | AO9: =AG9+AK9+AN9+AL9+AM9 -> 0 | AP9: =(V9*W9)+((50%*J9*Q9)+(K9*Q9)) -> 0 | AQ9: =BC9*$AQ$8 -> 0 | AR9: =AO9-AP9-AQ9 -> 0 | AT9: =AK9 -> 0 | AU9: =BD9*$AU$8 -> 0 | AV9: =AN9 -> 0 | AW9: =SUM(AS9:AV9) -> 0 | AX9: =AR9-AW9 -> 0 | AZ9: =AU9+AJ9 -> 0 | BA9: =AK9+AQ9-AJ9 -> 0 | BC9: 0 | BD9: 0
A10: =A9+1 -> 1 | U10: =X10*0.1 -> 0 | V10: =O10 -> 0 | Y10: =+P10*Q10 -> 0 | Z10: =+U10*T10 -> 0 | AA10: 2000000 | AB10: 200000 | AD10: 2000000 | AF10: =S10*R10 -> 0 | AG10: =SUM(X10:AF10) -> 4200000 | AH10: =$AH$8*BC10 -> 384750 | AI10: =$AI$8*BC10 -> 36450 | AJ10: =$AJ$8*BD10 -> 270000 | AK10: =SUM(AH10:AJ10) -> 691200 | AN10: =BF10 -> 0 | AO10: =AG10+AK10+AN10+AL10+AM10 -> 4891200 | AP10: =(V10*W10)+((50%*J10*Q10)+(K10*Q10)) -> 0 | AQ10: =BC10*$AQ$8 -> 202500 | AR10: =AO10-AP10-AQ10 -> 4688700 | AT10: =AK10 -> 691200 | AU10: =BD10*$AU$8 -> 67500 | AV10: =AN10 -> 0 | AW10: =SUM(AS10:AV10) -> 758700 | AX10: =AR10-AW10 -> 3930000 | AZ10: =AU10+AJ10 -> 337500 | BA10: =AK10+AQ10-AJ10 -> 623700 | BC10: 6750000 | BD10: 6750000
A11: =A10+1 -> 2 | U11: =X11*0.1 -> 0 | V11: =O11 -> 0 | Y11: =+P11*Q11 -> 0 | Z11: =+U11*T11 -> 0 | AF11: =S11*R11 -> 0 | AG11: =SUM(X11:AF11) -> 0 | AH11: =$AH$8*BC11 -> 326602.93 | AI11: =$AI$8*BC11 -> 30941.33 | AJ11: =$AJ$8*BD11 -> 229195.04 | AK11: =SUM(AH11:AJ11) -> 586739.3 | AN11: =BF11 -> 0 | AO11: =AG11+AK11+AN11+AL11+AM11 -> 586739.3 | AP11: =(V11*W11)+((50%*J11*Q11)+(K11*Q11)) -> 0 | AQ11: =BC11*$AQ$8 -> 171896.28 | AR11: =AO11-AP11-AQ11 -> 414843.02 | AT11: =AK11 -> 586739.3 | AU11: =BD11*$AU$8 -> 57298.76 | AV11: =AN11 -> 0 | AW11: =SUM(AS11:AV11) -> 644038.06 | AX11: =AR11-AW11 -> -229195.04 | AZ11: =AU11+AJ11 -> 286493.8 | BA11: =AK11+AQ11-AJ11 -> 529440.54 | BC11: 5729876 | BD11: 5729876
A12: =A11+1 -> 3 | U12: =X12*0.1 -> 0 | V12: =O12 -> 0 | Y12: =+P12*Q12 -> 0 | Z12: =+U12*T12 -> 0 | AF12: =S12*R12 -> 0 | AG12: =SUM(X12:AF12) -> 0 | AH12: =$AH$8*BC12 -> 326602.93 | AI12: =$AI$8*BC12 -> 30941.33 | AJ12: =$AJ$8*BD12 -> 229195.04 | AK12: =SUM(AH12:AJ12) -> 586739.3 | AN12: =BF12 -> 0 | AO12: =AG12+AK12+AN12+AL12+AM12 -> 586739.3 | AP12: =(V12*W12)+((50%*J12*Q12)+(K12*Q12)) -> 0 | AQ12: =BC12*$AQ$8 -> 171896.28 | AR12: =AO12-AP12-AQ12 -> 414843.02 | AT12: =AK12 -> 586739.3 | AU12: =BD12*$AU$8 -> 57298.76 | AV12: =AN12 -> 0 | AW12: =SUM(AS12:AV12) -> 644038.06 | AX12: =AR12-AW12 -> -229195.04 | AZ12: =AU12+AJ12 -> 286493.8 | BA12: =AK12+AQ12-AJ12 -> 529440.54 | BC12: 5729876 | BD12: 5729876
A13: =A12+1 -> 4 | U13: =X13*0.1 -> 0 | V13: =O13 -> 0 | Y13: =+P13*Q13 -> 0 | Z13: =+U13*T13 -> 0 | AF13: =S13*R13 -> 0 | AG13: =SUM(X13:AF13) -> 0 | AH13: =$AH$8*BC13 -> 326602.93 | AI13: =$AI$8*BC13 -> 30941.33 | AJ13: =$AJ$8*BD13 -> 229195.04 | AK13: =SUM(AH13:AJ13) -> 586739.3 | AN13: =BF13 -> 0 | AO13: =AG13+AK13+AN13+AL13+AM13 -> 586739.3 | AP13: =(V13*W13)+((50%*J13*Q13)+(K13*Q13)) -> 0 | AQ13: =BC13*$AQ$8 -> 171896.28 | AR13: =AO13-AP13-AQ13 -> 414843.02 | AT13: =AK13 -> 586739.3 | AU13: =BD13*$AU$8 -> 57298.76 | AV13: =AN13 -> 0 | AW13: =SUM(AS13:AV13) -> 644038.06 | AX13: =AR13-AW13 -> -229195.04 | AZ13: =AU13+AJ13 -> 286493.8 | BA13: =AK13+AQ13-AJ13 -> 529440.54 | BC13: 5729876 | BD13: 5729876
X14: =SUM(X9:X13) -> 0 | Y14: =SUM(Y9:Y13) -> 0 | Z14: =SUM(Z9:Z13) -> 0 | AA14: =SUM(AA9:AA13) -> 2000000 | AB14: =SUM(AB9:AB13) -> 200000 | AC14: =SUM(AC9:AC13) -> 0 | AD14: =SUM(AD9:AD13) -> 2000000 | AE14: =SUM(AE9:AE13) -> 0 | ... AK14: =SUM(AK9:AK13) -> 2451417.9 | AM14: =SUM(AM9:AM13) -> 0 | AN14: =SUM(AN9:AN13) -> 0 | AO14: =SUM(AO9:AO13) -> 6651417.9 | AP14: =SUM(AP9:AP13) -> 0 | AQ14: =SUM(AQ9:AQ13) -> 718188.84 | AR14: =SUM(AR9:AR13) -> 5933229.1 | AS14: =SUM(AS9:AS13) -> 0 | AT14: =SUM(AT9:AT13) -> 2451417.9 | ... BF14: =SUM(BF9:BF13) -> 0
A15: =A13+1 -> 5 | S15: =1000000/2 -> 500000 | Y15: =+P15*Q15 -> 0 | Z15: =+U15*T15 -> 0 | AA15: 2000000 | AD15: =4000000 -> 4000000 | AF15: =S15*R15 -> 0 | AG15: =SUM(X15:AF15) -> 6000000 | AH15: =$AH$8*BC15 -> 0 | AI15: =$AI$8*BC15 -> 0 | AJ15: =$AJ$8*BD15 -> 0 | AK15: =SUM(AH15:AJ15) -> 0 | AN15: =BF15 -> 0 | AO15: =AG15+AK15+AN15+AL15+AM15 -> 6000000 | AP15: =(V15*W15)+((50%*J15*Q15)+(K15*Q15)) -> 0 | AQ15: =BC15*$AQ$8 -> 0 | AR15: =AO15-AP15-AQ15 -> 6000000 | AT15: =AK15 -> 0 | AU15: =BD15*$AU$8 -> 0 | AV15: =AN15 -> 0 | AW15: =SUM(AS15:AV15) -> 0 | AX15: =AR15-AW15 -> 6000000 | AZ15: =AU15+AJ15 -> 0 | BA15: =AK15+AQ15-AJ15 -> 0
A16: =A15+1 -> 6 | S16: =20600000/2 -> 10300000 | Y16: =+P16*Q16 -> 0 | Z16: =+U16*T16 -> 0 | AA16: 1000000 | AD16: 1000000 | AF16: =S16*R16 -> 0 | AG16: =SUM(X16:AF16) -> 2000000 | AH16: =$AH$8*BC16 -> 326602.93 | AI16: =$AI$8*BC16 -> 30941.33 | AJ16: =$AJ$8*BD16 -> 229195.04 | AK16: =SUM(AH16:AJ16) -> 586739.3 | AN16: =BF16 -> 0 | AO16: =AG16+AK16+AN16+AL16+AM16 -> 2586739.3 | AP16: =(V16*W16)+((50%*J16*Q16)+(K16*Q16)) -> 0 | AQ16: =BC16*$AQ$8 -> 171896.28 | AR16: =AO16-AP16-AQ16 -> 2414843 | AT16: =AK16 -> 586739.3 | AU16: =BD16*$AU$8 -> 57298.76 | AV16: =AN16 -> 0 | AW16: =SUM(AS16:AV16) -> 644038.06 | AX16: =AR16-AW16 -> 1770805 | AZ16: =AU16+AJ16 -> 286493.8 | BA16: =AK16+AQ16-AJ16 -> 529440.54 | BC16: 5729876 | BD16: 5729876
A17: =A16+1 -> 7 | S17: =1110000+1486000 -> 2596000 | U17: =X17*0.1 -> 0 | V17: =O17 -> 0 | Y17: =+P17*Q17 -> 0 | Z17: =+U17*T17 -> 0 | AF17: =S17*R17 -> 0 | AG17: =SUM(X17:AF17) -> 0 | AH17: =$AH$8*BC17 -> 326602.93 | AI17: =$AI$8*BC17 -> 30941.33 | AJ17: =$AJ$8*BD17 -> 229195.04 | AK17: =SUM(AH17:AJ17) -> 586739.3 | AN17: =BF17 -> 0 | AO17: =AG17+AK17+AN17+AL17+AM17 -> 586739.3 | AP17: =(V17*W17)+((50%*J17*Q17)+(K17*Q17)) -> 0 | AQ17: =BC17*$AQ$8 -> 171896.28 | AR17: =AO17-AP17-AQ17 -> 414843.02 | AT17: =AK17 -> 586739.3 | AU17: =BD17*$AU$8 -> 57298.76 | AV17: =AN17 -> 0 | AW17: =SUM(AS17:AV17) -> 644038.06 | AX17: =AR17-AW17 -> -229195.04 | AZ17: =AU17+AJ17 -> 286493.8 | BA17: =AK17+AQ17-AJ17 -> 529440.54 | BC17: 5729876 | BD17: 5729876
A18: =A17+1 -> 8 | S18: =1090000+1162000 -> 2252000 | U18: =X18*0.1 -> 0 | V18: =O18 -> 0 | Y18: =+P18*Q18 -> 0 | Z18: =+U18*T18 -> 0 | AB18: 100000 | AF18: =S18*R18 -> 0 | AG18: =SUM(X18:AF18) -> 100000 | AH18: =$AH$8*BC18 -> 326602.93 | AI18: =$AI$8*BC18 -> 30941.33 | AJ18: =$AJ$8*BD18 -> 229195.04 | AK18: =SUM(AH18:AJ18) -> 586739.3 | AN18: =BF18 -> 0 | AO18: =AG18+AK18+AN18+AL18+AM18 -> 686739.3 | AP18: =(V18*W18)+((50%*J18*Q18)+(K18*Q18)) -> 0 | AQ18: =BC18*$AQ$8 -> 171896.28 | AR18: =AO18-AP18-AQ18 -> 514843.02 | AT18: =AK18 -> 586739.3 | AU18: =BD18*$AU$8 -> 57298.76 | AV18: =AN18 -> 0 | AW18: =SUM(AS18:AV18) -> 644038.06 | AX18: =AR18-AW18 -> -129195.04 | AZ18: =AU18+AJ18 -> 286493.8 | BA18: =AK18+AQ18-AJ18 -> 529440.54 | BC18: 5729876 | BD18: 5729876
A19: =A18+1 -> 9 | S19: =1005000+1464000 -> 2469000 | U19: =X19*0.1 -> 0 | V19: =O19 -> 0 | Y19: =+P19*Q19 -> 0 | Z19: =+U19*T19 -> 0 | AB19: 100000 | AF19: =S19*R19 -> 0 | AG19: =SUM(X19:AF19) -> 100000 | AH19: =$AH$8*BC19 -> 326602.93 | AI19: =$AI$8*BC19 -> 30941.33 | AJ19: =$AJ$8*BD19 -> 229195.04 | AK19: =SUM(AH19:AJ19) -> 586739.3 | AN19: =BF19 -> 0 | AO19: =AG19+AK19+AN19+AL19+AM19 -> 686739.3 | AP19: =(V19*W19)+((50%*J19*Q19)+(K19*Q19)) -> 0 | AQ19: =BC19*$AQ$8 -> 171896.28 | AR19: =AO19-AP19-AQ19 -> 514843.02 | AS19: 500000 | AT19: =AK19 -> 586739.3 | AU19: =BD19*$AU$8 -> 57298.76 | AV19: =AN19 -> 0 | AW19: =SUM(AS19:AV19) -> 1144038.1 | AX19: =AR19-AW19 -> -629195.04 | AZ19: =AU19+AJ19 -> 286493.8 | BA19: =AK19+AQ19-AJ19 -> 529440.54 | BC19: 5729876 | BD19: 5729876
X20: =SUM(X15:X19) -> 0 | Y20: =SUM(Y15:Y19) -> 0 | Z20: =SUM(Z15:Z19) -> 0 | AA20: =SUM(AA15:AA19) -> 3000000 | AB20: =SUM(AB15:AB19) -> 200000 | AC20: =SUM(AC15:AC19) -> 0 | AD20: =SUM(AD15:AD19) -> 5000000 | AE20: =SUM(AE15:AE19) -> 0 | ... BF20: =SUM(BF15:BF19) -> 0
X21: =X20+X14 -> 0 | Y21: =Y20+Y14 -> 0 | Z21: =Z20+Z14 -> 0 | AA21: =AA20+AA14 -> 5000000 | AB21: =AB20+AB14 -> 400000 | AC21: =AC20+AC14 -> 0 | AD21: =AD20+AD14 -> 7000000 | AE21: =AE20+AE14 -> 0 | ... BF21: =BF20+BF14 -> 0
AH22: =SUM(AH21:AJ21) -> 4798375.1 | AT22: =SUM(AT21:AT21) -> 4798375.1

Sheet New slip
B1: PT Demo Nusantara | N1: 5
B2: Salary Slip
B4: Personal Data | M4: =N1 -> 5
B5: Employee Name | F5: =VLOOKUP($E$13,June!$A$9:$BB$20,2) -> 0 | J5: Payroll Period | K5: : | L5: =June!AG2 -> June 2026
B6: Title | F6: =VLOOKUP($E$13,June!$A$9:$BB$20,4) -> 0 | J6: Cut Off Period | K6: : | L6: =June!AG3 -> 22Mayr s/d 21 June 2026
B7: Location | F7: =VLOOKUP($E$13,June!$A$9:$BB$20,5) -> 0 | J7: Sisa Cuti | K7: : | L7: =VLOOKUP($E$13,June!$A$9:$BF$20,9) -> 0
B8: Family Status | E8: : | F8: =VLOOKUP($E$13,June!$A$9:$BB$20,8) -> 0
B10: A. Fix Income : | H10: C. Deductible
C12: 1 | D12: Basic Salary | E12: : | F12: =VLOOKUP($E$13,June!$A$9:$BF$20,24) -> 0 | I12: =C27+1 -> 1 | J12: Absensi | K12: : | L12: =VLOOKUP($E$13,June!$A$9:$BF$20,42) -> 0
E13: =N1 -> 5
B14: B. Other Variable Incomes : | I14: 2 | J14: Potongan BPJS | K14: :
C15: 2 | D15: THR LEBARAN | E15: : | J15: - Tunj. Prshan | K15: : | L15: =VLOOKUP($E$13,June!$A$9:$BF$20,46) -> 0
C16: 2 | D16: Tunjangan PPh21 | E16: : | F16: =VLOOKUP($E$13,June!$A$9:$BF$20,40) -> 0 | J16: - Karyawan | K16: : | L16: =VLOOKUP($E$13,June!$A$9:$BF$20,43)+VLOOKUP($E$13,June!$A$9:$BF$20,47) -> 0
C17: =C16+1 -> 3 | D17: Uang Harian | E17: : | F17: =VLOOKUP($E$13,June!$A$9:$BF$20,25) -> 0 | I17: 3 | J17: Potongan PPh 21 | K17: : | L17: =F16 -> 0
C18: =C17+1 -> 4 | D18: Inctv Kerajinan | E18: : | F18: =VLOOKUP($E$13,June!$A$9:$BF$20,26) -> 0
C19: =C18+1 -> 5 | D19: Inctv Prestasi | E19: : | F19: =VLOOKUP($E$13,June!$A$9:$BF$20,31) -> 0
C20: =C19+1 -> 6 | D20: Tunj. Antar Cabang | E20: : | F20: =VLOOKUP($E$13,June!$A$9:$BF$20,27) -> 2000000 | I20: 4 | J20: Cicilan Pinjaman | K20: : | L20: =VLOOKUP($E$13,June!$A$9:$BF$20,45) -> 0
C21: =C20+1 -> 7 | D21: Tunj. Komunikasi | E21: : | F21: =VLOOKUP($E$13,June!$A$9:$BF$20,28) -> 0 | I21: 5 | J21: Lain-2 | K21: : | L21: 0
C22: =C21+1 -> 8 | D22: Tunj. Kost/Obat | E22: : | F22: =VLOOKUP($E$13,June!$A$9:$BF$20,29) -> 0
C23: =C22+1 -> 9 | D23: Tunj. Jabatan | E23: : | F23: =VLOOKUP($E$13,June!$A$9:$BF$20,30) -> 4000000
C24: =C23+1 -> 10 | D24: Lembur & Perdin | E24: : | F24: =VLOOKUP($E$13,June!$A$9:$BF$20,32) -> 0
C25: =C24+1 -> 11 | D25: Tunjangan BPJS | E25: : | F25: =VLOOKUP($E$13,June!$A$9:$BF$20,37) -> 0
C26: =C25+1 -> 12 | D26: THR LEBARAN | E26: : | F26: =VLOOKUP($E$13,June!$A$9:$BF$20,38) -> 0
C29: Penghasilan Bruto | E29: : | F29: =SUM(F12:F28) -> 6000000 | H29: D. Total THP | K29: : | L29: =F29-(SUM(L12:L21)) -> 6000000

Sheet REKAP
D5: PT DEMO NUSANTARA
B7: REKAP GAJI BULAN : June 2026
B8: PEMBAYARAN TANGGAL : 30 June 26
E12: NO | F12: KETERANGAN | I12: RINCIAN | J12: JUMLAH
J13: Rp.
E15: 0 | F15: PENDAPATAN GROSS | I15: =June!A19 -> 9 | J15: =June!AO21-June!AP21 -> 17198375 | N15: Iuran BPJS
N16: TK | O16: 0 | P16: =June!BA21 -> 4329783.8
E17: 0 | F17: POTONGAN | H17: a. Pinjaman | I17: =June!AS21 -> 500000 | N17: Kes | O17: 0 | P17: =June!AZ21 -> 2342956.6
H18: b. Jamsostek | I18: =June!AQ21+June!AT21+June!AU21 -> 6672740.4 | J18: =+I17+I18+I19 -> 7172740.4 | O18: =SUM(O16:O17) -> 0 | P18: =SUM(P16:P17) -> 6672740.4
H19: c. Tax | I19: =June!AV21 -> 0 | O19: =O18-I18 -> -6672740.4 | P19: =P18-I18 -> 0
E20: 0 | F20: PENDAPATAN NET | J20: =+J15-J18 -> 10025635
F22: RINCIAN PEMBAYARAN :
E24: 0 | F24: Transfer via bank Permata | H24: =I15-H25 -> 9 | I24: =June!AX21-REKAP!I25 -> 10025635
E25: 0 | F25: Tunai | H25: 0 | I25: =N31 -> 0 | J25: =+I24+I25 -> 10025635
H26: =+I15-H24-H25 -> 0 | J26: =+J20-J25 -> 3.7252903e-09 | M26: Cash
L28: 0 | N28: 0
D31: Jakarta, 25 June 2026 | N31: =SUM(N27:N30) -> 0
D33: Dibuat oleh : | H33: Diperiksa oleh : | J33: Diketahui oleh :
D39: HR & GA Manager
